garf/__init__.py
garf/garf_detector.py
garf/garf_model.py
garf/garf_train.py
garf/helpers.py
garf/bin/__init__.py
garf/bin/garf_compare_image_profile.py
garf/bin/garf_nn_info.py
garf/bin/garf_plot_test_dataset.py
garf/bin/garf_plot_training_dataset.py
garf/bin/garf_train.py
garf/bin/pytorch_info.py
garf-2.10.dist-info/licenses/LICENSE
garf-2.10.dist-info/METADATA
garf-2.10.dist-info/WHEEL
garf-2.10.dist-info/entry_points.txt
garf-2.10.dist-info/top_level.txt
garf-2.10.dist-info/RECORD
