Metadata-Version: 2.4
Name: garf
Version: 2.10
Summary: Utility tools for GATE ARF simulations
Author-email: David Sarrut <david.sarrut@creatis.insa-lyon.fr>
License:                                  Apache License
Classifier: Programming Language :: Python :: 3
Classifier: License :: OSI Approved :: Apache Software License
Classifier: Operating System :: OS Independent
Requires-Python: >=3.8
License-File: LICENSE
Requires-Dist: itk
Requires-Dist: numpy
Requires-Dist: pre-commit
Requires-Dist: torch>=2.1.0
Requires-Dist: tqdm
Dynamic: license-file
